bujango
